MANIFEST.in
README.md
requirements.txt
setup.cfg
setup.py
daydreamer/__init__.py
daydreamer/apiclient.py
daydreamer/baseclient.py
daydreamer/compat.py
daydreamer/enums.py
daydreamer/exceptions.py
daydreamer/utils.py
daydreamer.egg-info/PKG-INFO
daydreamer.egg-info/SOURCES.txt
daydreamer.egg-info/dependency_links.txt
daydreamer.egg-info/requires.txt
daydreamer.egg-info/top_level.txt
daydreamer/endpoints/__init__.py
daydreamer/endpoints/account.py
daydreamer/endpoints/baseendpoint.py
daydreamer/endpoints/betting.py
daydreamer/endpoints/marketdata.py
daydreamer/endpoints/referencedata.py
daydreamer/resources/__init__.py
daydreamer/resources/accountresources.py
daydreamer/resources/baseresource.py
daydreamer/resources/bettingresources.py
daydreamer/resources/marketdataresources.py
daydreamer/resources/referencedataresources.py
daydreamer/tests/__init__.py
daydreamer/tests/test_account.py
daydreamer/tests/test_apiclient.py
daydreamer/tests/test_baseclient.py
daydreamer/tests/test_betting.py
daydreamer/tests/test_marketdata.py
daydreamer/tests/test_referencedata.py
daydreamer/tests/test_utils.py