Metadata-Version: 1.0
Name: daydreamer
Version: 0.0.16
Summary: Daydreamer Nick API Python wrapper
Home-page: https://github.com/rozzac90/pinnacle
Author: Nick Georgiadis
Author-email: nickgeo_@hotmail.com
License: UNKNOWN
Platform: UNKNOWN
